dbstorage/__init__.py
dbstorage/admin.py
dbstorage/apps.py
dbstorage/forms.py
dbstorage/migrations/0001_initial.py
dbstorage/migrations/0002_remove_dbfile_size_dbfile_accessed_on_and_more.py
dbstorage/migrations/__init__.py
dbstorage/models.py
dbstorage/storage.py
dbstorage/urls.py
dbstorage/views.py
django_blob_storage-0.2.2.dist-info/LICENSE.md
django_blob_storage-0.2.2.dist-info/METADATA
django_blob_storage-0.2.2.dist-info/WHEEL
django_blob_storage-0.2.2.dist-info/RECORD
