Metadata-Version: 2.1
Name: django-blob-storage
Version: 0.2.2
Summary: 
License: BSD
Author: alex
Author-email: devkral@web.de
Requires-Python: >=3.9,<4.0
Classifier: License :: Other/Proprietary License
Classifier: Programming Language :: Python :: 3
Classifier: Programming Language :: Python :: 3.9
Classifier: Programming Language :: Python :: 3.10
Classifier: Programming Language :: Python :: 3.11
Requires-Dist: django (>=3.2)
